{
    "title": "Church 21: Adapting to Change",
    "date": "2010-06-13",
    "blurb": "In this sermon, Kevin discusses the importance of adapting to change, using the metaphor of a battleship changing course. He highlights how the Church, like society, has had to adjust to new realities, such as multiculturalism, secularism, and technological advancements. He also outlines the efforts of the Church of Ireland's Parish Development Organisation, Church 21, to respond to these changes.",
    "raw_text": "Start with 'battleship' video clip. This raises the issue of the importance of responding to changing situations, new insights, new information. Politicians in the UK have had to come to terms with the new political realities of hung Parliaments and Coalitions. We have all been affected to a greater or lesser extent by the financial downturn. Governments have had to be more proactive in control of banks and financial institutions. Reduced incomes, drop in house prices & negative equity \u2013 we have had to change our way of doing things. Purchase of new car, meals out, trips away have been scaled back \u2013 like the battleship we have had to change course.\n\nChurch is operating in very different circumstances to 10 or 20 years ago. Ireland is now very much a multicultural society and also a far more secular society. There's an explosion in the whole field of communication, more mobile population, more pressurised work place, and a greater willingness to question and to challenge.\n\nChurch of Ireland, in an effort to enable Parishes to respond to these and other changes, established Church 21, the Parish Development Organisation. Beginning of last year Howth Parish embarked upon a programme. Lenten Groups followed a programme designed to get us thinking about the various issues facing a Parish as it seeks to respond to changing circumstances.\n\nThere are many positives to our Parish. We are a warm and welcoming community \u2013 people identified the Fete, the coffees after Church, the midweek service. We are inclusive and non-judgemental. We have an attractive Church and Parish Centre that is used and valued by both the Parish and the wider community. We have a strong Sunday School and a strong link with the Burrow National School.\n\nWe have identified a number of specific initiatives designed to build on our strengths and address some of our weaknesses. Parish Website is ready to be relaunched \u2013 this will provide news about current events and services, text of recent sermons, groups using the Parish Centre, details of marriage and baptism services in the Parish. We are investigating a more prominent sign closer to the road. A Prayer group has been established that meets each Sunday after Church.\n\nA group is being formed to coordinate a series of activities for the older age group. This will provide a combination of day trips, talks on subjects of interest and activities in the Parish Centre that provide an opportunity to come together, relax and enjoy each other\u2019s company. In the autumn there will be a beginner\u2019s course in computing in the Burrow School computer suite. This will be delivered by Linda Frost and support will be provided by members of our Youth Club.",
    "request": {
        "file_name": "raw/sermons archive/Sermons/Special Occasions/Proper//Year C/proper5church 21.txt",
        "raw_ocr_content": "Page 1 of 4\nProper 5 \u2013 2010 \u2013 year C\nChurch 21\nStart with \u2018battleship\u2019 video clip\nhttp://www.youtube.com/watch?v=Knu14TlvCQE\nSLIDE 1 + 2\nRaises issue of the importance of responding to changing situation,\nnew insights, new information\nSLIDE 3\nPoliticians in the UK have had to come to terms with the new political\nrealities of hung Parliaments and Coalitions.\nSLIDE 4\nWe have all been affected to a greater of lesser extent by the financial\ndownturn\nGovernments have had to be more proactive in control of banks and\nfinancial institutions.\nReduced incomes, drop in house prices & negative equity \u2013 we have\nhad to change our way of doing things\npurchase of new car, meals out, trips away have been scaled back \u2013\nlike the battleship we have had to change course.\nChurch is operating in very different circumstances to 10 or 20 years\nago. Ireland is now very much a multicultural society and also a far\nmore secular society.\nSLIDE 5\nexplosion in the whole field of communication\nmore mobile population\nmore pressurised work place\ngreater willingness to question and to challenge\nSLIDE 6\nC of I in an effort to enable Parishes to respond to these and other\nchanges established Church 21, the Parish Development Organisation\nBeginning of last year Howth Parish embarked upon a programme.\nPage 2 of 4\nProper 5 \u2013 2010 \u2013 year C\nChurch 21\nSLIDE 7\nLenten Groups followed a programme designed to get us thinking\nabout the various issues facing a Parish as it seeks to respond to\nchanging circumstances.\nMyself, Troy Hopkins, Shaz Basdeo, Helen McVeigh and Shirley\nMoon attended a conference in September that drew together all the\nParishes participating in the current programme.\nThis has been followed by a period of reflection in which we have\ntried to identify a number of key objectives for the Parish.\nSLIDE 8\nThere are many positives to our Parish.\nWe are a warm and welcoming community \u2013 people identified the\nFete, the coffees after Church, the midweek service\nWe are inclusive and non-judgemental.\nWe have an attractive Church and Parish Centre that is used and\nvalued by both the Parish and the wider community.\nWe have a strong Sunday School\nStrong link with the Burrow National School\nSLIDE 9\nRecognised a number of challenges as a Parish\nWe have not connected with our post confirmation groups.\nAge imbalance in our Sunday congregation\nWe have lost over the years a number of groups that bring people\ntogether for social contact \u2013 e.g. Mothers Union, Burrow Players\nWe are not good at providing opportunities for groups to reflect on\ntheir faith.\nWe are not good at communicating who we are.\nPeople expressed an interest in finding areas of service to the\ncommunity.\nPage 3 of 4\nProper 5 \u2013 2010 \u2013 year C\nChurch 21\nWhere do we go now\nSLIDE 10\nSLIDE 11\nWe have already made a start in the area of our ministry to youth. The\nappointment of Shaz Basdeo and now Stephen Byford has had a major\nimpact. Confirmation Group has formed the core of a Youth Club that\nmeets each Tuesday night with about 15-20 people turning up.\nSLIDE 12\nWe have identified a number of specific initiatives designed to build\non our strengths and address some of our weaknesses.\nSLIDE 13 Communication\nParish Website is ready to be relaunched \u2013 this will provide news\nabout current events and services, text of recent sermons, groups using\nthe Parish Centre , details of marriage and baptism services in the\nParish\nWe are investigating a more prominent sign closer to the road.\nSLIDE 14 Spirituality\nPrayer group has been established that meets each Sunday after\nChurch.\nThere will be a Networking Course run in the autumn \u2013 this provides a\nformat for a series of meetings in which participants are enabled to\nidentify their own particular gifts within the Church \u2013 such a course\nwas run during Cecil\u2019s time in the Parish.\nThe Alpha Ireland Organisation are launching a campaign in the new\nyear. This will be principally directed at the age range 20-40 and will\nbe supported by an advertising campaign. We have expressed an\ninterest in linking in with this campaign.\nPage 4 of 4\nProper 5 \u2013 2010 \u2013 year C\nChurch 21\nSLIDE 15 Building Community\nA group is being formed to coordinate a series of activities for the\nolder age group. This will provide a combination of day trips, talks on\nsubjects of interest and activities in the Parish Centre that provide an\nopportunity to come together, relax and enjoy each other\u2019s company.\nSLIDE 16 Service\nIn the autumn there will be a beginner\u2019s course in computing in the\nBurrow School computer suite. This will be delivered by Linda Frost\nand support will be provided by members of our Youth Club.\nWe offer this as a work in progress. Troy and I would love to hear\ncomments, suggestions, criticisms over coffee after the 11 o\u2019clock\nservice."
    },
    "prompt": "Create a detailed black and white pencil sketch that illustrates the concept of adaptability to change. The image should feature a large, majestic tree with roots deeply embedded in the ground, symbolizing stability. The tree's branches are robust but flexible, bending in various directions to represent responsiveness to changing conditions. Each branch ends with a different scene: one with leaves adapting to the seasons, another sprouting blossoms, one with a bird's nest showcasing new life, and another with a branch being pruned to encourage growth. The background should be minimalistic, with gentle wind lines indicating the direction of change. No human figures, religious symbols, or text should be included. The overall tone of the sketch should convey resilience, growth, and the natural flow of transformation.",
    "summary": "Based on the sermon provided, here are the top 4 concepts:\n\n1. Adaptability to Change: The sermon discusses the importance of responding to changing situations, such as political shifts, economic downturns, and societal changes. This concept emphasizes the need for flexibility and the ability to pivot in response to new information and circumstances.\n\n2. Community and Inclusivity: The sermon highlights the positive aspects of the parish, describing it as a warm, welcoming, and non-judgmental community. This concept focuses on the strength of communal ties and the value of inclusiveness within a diverse society.\n\n3. Communication and Outreach: The relaunch of the Parish website and the consideration of a more prominent sign indicate an effort to improve communication and outreach. This concept is about connecting with the community and sharing information effectively.\n\n4. Support for the Elderly: The formation of a group to coordinate activities for the older age group suggests a focus on providing support and engagement for seniors. This concept deals with the importance of caring for the well-being of the elderly in the community.\n\nFor a non-religious black and white pencil diagram that can be graphically represented, I would select the concept of \"Adaptability to Change.\" This concept is broad and can be visually depicted without religious symbolism.\n\n**Detailed Prompt for DALL-E 3:**\n\n\"Create a detailed black and white pencil sketch that illustrates the concept of adaptability to change. The image should feature a large, majestic tree with roots deeply embedded in the ground, symbolizing stability. The tree's branches are robust but flexible, bending in various directions to represent responsiveness to changing conditions. Each branch ends with a different scene: one with leaves adapting to the seasons, another sprouting blossoms, one with a bird's nest showcasing new life, and another with a branch being pruned to encourage growth. The background should be minimalistic, with gentle wind lines indicating the direction of change. No human figures, religious symbols, or text should be included. The overall tone of the sketch should convey resilience, growth, and the natural flow of transformation.\""
}